LICENSE
MANIFEST.in
README.rst
setup.py
backtalk/__init__.py
backtalk/admin.py
backtalk/feeds.py
backtalk/forms.py
backtalk/managers.py
backtalk/models.py
backtalk/moderation.py
backtalk/signals.py
backtalk/urls.py
backtalk/locale/af/LC_MESSAGES/django.mo
backtalk/locale/af/LC_MESSAGES/django.po
backtalk/locale/ar/LC_MESSAGES/django.mo
backtalk/locale/ar/LC_MESSAGES/django.po
backtalk/locale/az/LC_MESSAGES/django.mo
backtalk/locale/az/LC_MESSAGES/django.po
backtalk/locale/be/LC_MESSAGES/django.mo
backtalk/locale/be/LC_MESSAGES/django.po
backtalk/locale/bg/LC_MESSAGES/django.mo
backtalk/locale/bg/LC_MESSAGES/django.po
backtalk/locale/bn/LC_MESSAGES/django.mo
backtalk/locale/bn/LC_MESSAGES/django.po
backtalk/locale/br/LC_MESSAGES/django.mo
backtalk/locale/br/LC_MESSAGES/django.po
backtalk/locale/bs/LC_MESSAGES/django.mo
backtalk/locale/bs/LC_MESSAGES/django.po
backtalk/locale/ca/LC_MESSAGES/django.mo
backtalk/locale/ca/LC_MESSAGES/django.po
backtalk/locale/cs/LC_MESSAGES/django.mo
backtalk/locale/cs/LC_MESSAGES/django.po
backtalk/locale/cy/LC_MESSAGES/django.mo
backtalk/locale/cy/LC_MESSAGES/django.po
backtalk/locale/da/LC_MESSAGES/django.mo
backtalk/locale/da/LC_MESSAGES/django.po
backtalk/locale/de/LC_MESSAGES/django.mo
backtalk/locale/de/LC_MESSAGES/django.po
backtalk/locale/el/LC_MESSAGES/django.mo
backtalk/locale/el/LC_MESSAGES/django.po
backtalk/locale/en/LC_MESSAGES/django.mo
backtalk/locale/en/LC_MESSAGES/django.po
backtalk/locale/en_GB/LC_MESSAGES/django.mo
backtalk/locale/en_GB/LC_MESSAGES/django.po
backtalk/locale/eo/LC_MESSAGES/django.mo
backtalk/locale/eo/LC_MESSAGES/django.po
backtalk/locale/es/LC_MESSAGES/django.mo
backtalk/locale/es/LC_MESSAGES/django.po
backtalk/locale/es_AR/LC_MESSAGES/django.mo
backtalk/locale/es_AR/LC_MESSAGES/django.po
backtalk/locale/es_MX/LC_MESSAGES/django.mo
backtalk/locale/es_MX/LC_MESSAGES/django.po
backtalk/locale/et/LC_MESSAGES/django.mo
backtalk/locale/et/LC_MESSAGES/django.po
backtalk/locale/eu/LC_MESSAGES/django.mo
django_backtalk.egg-info/PKG-INFO
django_backtalk.egg-info/SOURCES.txt
django_backtalk.egg-info/dependency_links.txt
django_backtalk.egg-info/top_level.txt