Metadata-Version: 1.1
Name: django-backtalk
Version: 1.0
Summary: A very simple comment app, forked from django.contrib.comments.
Home-page: http://dusette.net/
Author: Ronin Dusette
Author-email: contact@dusette.net
License: GPL v3
Platform: UNKNOWN
Classifier: Environment :: Web Environment
Classifier: Framework :: Django
Classifier: Intended Audience :: Developers
Classifier: Operating System :: OS Independent
Classifier: Programming Language :: Python
Classifier: Programming Language :: Python :: 2.6
Classifier: Programming Language :: Python :: 2.7
Classifier: Topic :: Internet :: WWW/HTTP
Classifier: Topic :: Internet :: WWW/HTTP :: Dynamic Content
